eqxvision/__init__.py
eqxvision/experimental.py
eqxvision/utils.py
eqxvision/layers/__init__.py
eqxvision/layers/conv_norm_activation.py
eqxvision/layers/drop_path.py
eqxvision/layers/extensions_2d.py
eqxvision/layers/mlps.py
eqxvision/layers/patch_embed.py
eqxvision/layers/squeeze.py
eqxvision/models/__init__.py
eqxvision/models/classification/__init__.py
eqxvision/models/classification/alexnet.py
eqxvision/models/classification/convnext.py
eqxvision/models/classification/densenet.py
eqxvision/models/classification/efficientnet.py
eqxvision/models/classification/googlenet.py
eqxvision/models/classification/mobilenetv2.py
eqxvision/models/classification/mobilenetv3.py
eqxvision/models/classification/regnet.py
eqxvision/models/classification/resnet.py
eqxvision/models/classification/shufflenetv2.py
eqxvision/models/classification/squeezenet.py
eqxvision/models/classification/swin.py
eqxvision/models/classification/vgg.py
eqxvision/models/classification/vit.py
eqxvision/models/segmentation/__init__.py
eqxvision/models/segmentation/_utils.py
eqxvision/models/segmentation/deeplabv3.py
eqxvision/models/segmentation/fcn.py
eqxvision/models/segmentation/lraspp.py
eqxvision-0.2.8.dist-info/entry_points.txt
eqxvision-0.2.8.dist-info/LICENSE.md
eqxvision-0.2.8.dist-info/WHEEL
eqxvision-0.2.8.dist-info/METADATA
eqxvision-0.2.8.dist-info/RECORD
