Metadata-Version: 2.1
Name: eqxvision
Version: 0.2.8
Summary: Root package info.
Author-email: Contributing Authors <aditya.91.singh@gmail.com>
Requires-Python: >=3.8
Classifier: License :: OSI Approved :: MIT License
Classifier: Operating System :: OS Independent
Classifier: Programming Language :: Python :: 3 :: Only
Requires-Dist: equinox >= 0.7.0
Requires-Dist: torch >=1.7.1
Requires-Dist: torchvision >=0.8.0
Requires-Dist: jinja2==3.0.3 ; extra == "docs"
Requires-Dist: Markdown>=3.3 ; extra == "docs"
Requires-Dist: MarkupSafe>=1.1 ; extra == "docs"
Requires-Dist: mkdocs>=1.2 ; extra == "docs"
Requires-Dist: mkdocs-autorefs>=0.3.1 ; extra == "docs"
Requires-Dist: pymdown-extensions>=6.3 ; extra == "docs"
Requires-Dist: mkdocs==1.3.0 ; extra == "docs"
Requires-Dist: mkdocs-autorefs ; extra == "docs"
Requires-Dist: mkdocs_include_exclude_files==0.0.1 ; extra == "docs"
Requires-Dist: mkdocs-material==7.3.6 ; extra == "docs"
Requires-Dist: mkdocs-material-extensions ; extra == "docs"
Requires-Dist: mkdocstrings==0.17.0 ; extra == "docs"
Requires-Dist: mkdocstrings-python ; extra == "docs"
Requires-Dist: mkdocstrings-python-legacy ; extra == "docs"
Requires-Dist: mknotebooks==0.7.1 ; extra == "docs"
Requires-Dist: pymdown-extensions==9.4 ; extra == "docs"
Requires-Dist: pytkdocs_tweaks==0.0.5 ; extra == "docs"
Requires-Dist: pre-commit ; extra == "test"
Requires-Dist: bluepy ; extra == "test"
Requires-Dist: pytest ; extra == "test"
Requires-Dist: equinox >= 0.7.0 ; extra == "test"
Requires-Dist: torch >=1.7.1 ; extra == "test"
Requires-Dist: torchvision >=0.8.0 ; extra == "test"
Requires-Dist: optax ; extra == "test"
Project-URL: Bug Tracker, https://github.com/paganpasta/eqxvision/issues
Project-URL: Homepage, https://github.com/paganpasta/eqxvision
Provides-Extra: docs
Provides-Extra: test
